poetry_truststore/__init__.py
poetry_truststore/plugin.py
poetry_truststore-0.1.0.dist-info/entry_points.txt
poetry_truststore-0.1.0.dist-info/METADATA
poetry_truststore-0.1.0.dist-info/WHEEL
poetry_truststore-0.1.0.dist-info/RECORD
